Workbook

Sheet GivenData
A4: Jan. 1 | B4: Beginning inventory | C4: 600 | D4: units @ | E4: 105 | F4: = | G4: =C4*E4 -> 63000
A5: Feb. 13 | B5: Purchased | C5: 200 | D5: units @ | E5: 109 | F5: = | G5: =C5*E5 -> 21800
A6: Aug. 5 | B6: Purchased | C6: 345 | D6: units @ | E6: 112 | F6: = | G6: =C6*E6 -> 38640
A8: Sales price per unit | C8: 165
A10: Sales units
A11: Feb. 15 | C11: 300 | D11: units
A12: Aug. 10 | C12: 335 | D12: units
A14: Additional data for Part 2:
A15: Sales units
A16: Feb. 15 | C16: 175 | D16: units from beginning inventory and
C17: 125 | D17: units from the Feb. 13 purchase
A18: Aug. 10 | C18: 15 | D18: units from beginning inventory and
C19: 320 | D19: units from the Aug. 5 purchase

Sheet Part 1a-FIFO
A5: Part 1a
A6: FIFO perpetual
B7: Purchases | E7: Sales (at cost) | H7: Balance
A8: Date | B8: Units | C8: Unit Cost | D8: Total Cost | E8: Units | F8: Unit Cost | G8: Cost of Goods Sold | H8: Units | I8: Unit Cost | J8: Total Cost
A9: =GivenData!A4 -> Jan. 1 | B9: Beginning inventory:
B10: =GivenData!C4 -> 600 | C10: =GivenData!E4 -> 105 | D10: =B10*C10 -> 63000 | H10: =+B10 -> 600 | I10: =+C10 -> 105 | J10: =+I10*H10 -> 63000
A12: =GivenData!A5 -> Feb. 13 | H12: =+H10 -> 600 | I12: =+I10 -> 105 | J12: =+J10 -> 63000
B13: 200 | C13: 109 | D13: =+C13*B13 -> 21800 | H13: =+B13 -> 200 | I13: =+C13 -> 109 | J13: =+D13 -> 21800
A15: =GivenData!A11 -> Feb. 15 | E15: 300 | F15: 105 | G15: =+E15*F15 -> 31500 | H15: =+H12-E15 -> 300 | I15: =+I12 -> 105 | J15: =+H15*I15 -> 31500
H16: =+H13 -> 200 | I16: =+I13 -> 109 | J16: =+I16*H16 -> 21800
A18: =GivenData!A6 -> Aug. 5 | H18: =+H15 -> 300 | I18: =+I15 -> 105 | J18: =+J15 -> 31500
H19: =+H16 -> 200 | I19: =+I16 -> 109 | J19: =+J16 -> 21800
B20: 345 | C20: 112 | D20: =+B20*C20 -> 38640 | H20: =+B20 -> 345 | I20: =+C20 -> 112 | J20: =+H20*I20 -> 38640
A21: =GivenData!A12 -> Aug. 10 | E21: 300 | F21: =+I18 -> 105 | G21: =+E21*F21 -> 31500
E22: 35 | F22: =+I19 -> 109 | G22: =+E22*F22 -> 3815 | H22: =+H19-E22 -> 165 | I22: =+I19 -> 109 | J22: =+H22*I22 -> 17985
H23: =+H20 -> 345 | I23: =+I20 -> 112 | J23: =+H23*I23 -> 38640
A24: Totals | B24: =SUM(B10:B23) -> 1145 | D24: =SUM(D10:D23) -> 123440 | E24: =SUM(E15:E23) -> 635 | G24: =SUM(G13:G23) -> 66815 | H24: =+H22+H23 -> 510 | J24: =SUM(J22:J23) -> 56625
E25: Cost of Goods Sold | H25: Ending Inventory

Sheet Part 1b-Weighted Average
A5: Part 1b
A6: Moving weighted average (round to the nearest whole cent)
B7: Purchases | E7: Sales (at cost) | H7: Balance
A8: Date | B8: Units | C8: Unit Cost | D8: Total Cost | E8: Units | F8: Unit Cost | G8: Cost of Goods Sold | H8: Units | I8: Unit Cost | J8: Total Cost
A9: =GivenData!A4 -> Jan. 1 | B9: Beginning inventory:
B10: =GivenData!C4 -> 600 | C10: =GivenData!E4 -> 105 | D10: =B10*C10 -> 63000 | H10: =+B10 -> 600 | I10: =+J10/H10 -> 105 | J10: =+D10 -> 63000
A12: =GivenData!A5 -> Feb. 13 | H12: =+H10 -> 600 | J12: =+J10 -> 63000
B13: 200 | C13: 109 | D13: =+C13*B13 -> 21800 | H13: =+B13 -> 200 | J13: =+D13 -> 21800
H14: =SUM(H12:H13) -> 800 | I14: =+J14/H14 -> 106 | J14: =SUM(J12:J13) -> 84800
A15: =GivenData!A11 -> Feb. 15 | H15: =+H14 -> 800 | J15: =+J14 -> 84800
E16: 300 | F16: =+I14 -> 106 | G16: =+E16*F16 -> 31800 | H16: =-1*E16 -> -300 | J16: =-1*G16 -> -31800
H17: =SUM(H15:H16) -> 500 | I17: =+J17/H17 -> 106 | J17: =SUM(J15:J16) -> 53000
A18: =GivenData!A6 -> Aug. 5 | H18: =+H17 -> 500 | J18: =+J17 -> 53000
H19: =+B20 -> 345 | J19: =+D20 -> 38640
B20: 345 | C20: 112 | D20: =+B20*C20 -> 38640 | H20: =SUM(H18:H19) -> 845 | I20: =+J20/H20 -> 108.4497 | J20: =SUM(J18:J19) -> 91640
A21: =GivenData!A12 -> Aug. 10 | H21: =+H20 -> 845 | J21: =+J20 -> 91640
E22: 335 | F22: =+I20 -> 108.4497 | G22: =+E22*F22 -> 36330.651 | H22: =-1*E22 -> -335 | J22: =-1*G22 -> -36330.651
H23: =SUM(H21:H22) -> 510 | I23: =+J23/H23 -> 108.4497 | J23: =SUM(J21:J22) -> 55309.349
A24: Totals | G24: =SUM(G15:G23) -> 68130.651
E25: Cost of Goods Sold | H25: Ending Inventory

Sheet Part 2-Specific ID
A5: Part 2
A6: Specific Identification
B7: Purchases | E7: Sales (at cost) | H7: Balance
A8: Date | B8: Units | C8: Unit Cost | D8: Total Cost | E8: Units | F8: Unit Cost | G8: Cost of Goods Sold | H8: Units | I8: Unit Cost | J8: Total Cost
A9: =GivenData!A4 -> Jan. 1 | B9: Beginning inventory:
B10: =GivenData!C4 -> 600 | C10: =GivenData!E4 -> 105 | D10: =B10*C10 -> 63000 | H10: =+B10 -> 600 | I10: =+C10 -> 105 | J10: =+I10*H10 -> 63000
A12: =GivenData!A5 -> Feb. 13 | H12: =+H10 -> 600 | I12: =+I10 -> 105 | J12: =+J10 -> 63000
B13: 200 | C13: 109 | D13: =+C13*B13 -> 21800 | H13: =+B13 -> 200 | I13: =+C13 -> 109 | J13: =+D13 -> 21800
A15: =GivenData!A11 -> Feb. 15 | E15: 175 | F15: 105 | G15: =+E15*F15 -> 18375 | H15: =+H12-E15 -> 425 | I15: =+I12 -> 105 | J15: =+H15*I15 -> 44625
E16: 125 | F16: =+I13 -> 109 | G16: =+E16*F16 -> 13625 | H16: =+H13-E16 -> 75 | I16: =+I13 -> 109 | J16: =+J13-G16 -> 8175
E17: =SUM(E15:E16) -> 300 | G17: =SUM(G15:G16) -> 32000
A18: =GivenData!A6 -> Aug. 5 | H18: =+H15 -> 425 | I18: =+I15 -> 105 | J18: =+J15 -> 44625
H19: =+H16 -> 75 | I19: =+I16 -> 109 | J19: =+J16 -> 8175
B20: 345 | C20: 112 | D20: =+B20*C20 -> 38640 | H20: =+B20 -> 345 | I20: =+C20 -> 112 | J20: =+H20*I20 -> 38640
A21: =GivenData!A12 -> Aug. 10 | E21: 15 | F21: =+I18 -> 105 | G21: =+E21*F21 -> 1575 | H21: =+H18-E21 -> 410 | I21: =+I18 -> 105 | J21: =+J18-G21 -> 43050
H22: =+H19 -> 75 | I22: =+I19 -> 109 | J22: =+H22*I22 -> 8175
E23: 320 | F23: =+I20 -> 112 | G23: =+E23*F23 -> 35840 | H23: =+H20-E23 -> 25 | I23: =+I20 -> 112 | J23: =+I23*H23 -> 2800
A24: Totals | G24: =SUM(G17:G23) -> 69415 | J24: =SUM(J21:J23) -> 54025
E25: Cost of Goods Sold | H25: Ending Inventory

Sheet Part 3
A4: Part 3
A5: Journalize sale and purchase
C6: FIFO | E6: Moving Weighted Average | G6: Specific Identification
A7: Date | B7: Account Titles | C7: Debit | D7: Credit | E7: Debit | F7: Credit | G7: Debit | H7: Credit
A8: =GivenData!A11 -> Feb. 15 | B8: Accounts Receivable | C8: =+F14*'Part 1a-FIFO'!E15 -> 49500 | E8: =+D9 -> 49500 | G8: =+D9 -> 49500
B9: Sales | D9: =+C8 -> 49500 | F9: =+E8 -> 49500 | H9: =+G8 -> 49500
A11: =A8 -> Feb. 15 | B11: Cost of Goods Sold | C11: =+'Part 1a-FIFO'!G15 -> 31500 | E11: =+'Part 1b-Weighted Average'!G16 -> 31800 | G11: =+'Part 2-Specific ID'!G17 -> 32000
B12: Merchandise Inventory | D12: =+C11 -> 31500 | F12: =+E11 -> 31800 | H12: =+G11 -> 32000
B14: To record sale of merchandise on credit. The selling price: | F14: 165
A15: Aug. 5 | B15: Merchandise Inventory | C15: =+'Part 1a-FIFO'!D20 -> 38640 | E15: =+C15 -> 38640 | G15: =+C15 -> 38640
B16: Accounts Payable | D16: =+C15 -> 38640 | F16: =+C15 -> 38640 | H16: =+C15 -> 38640
B21: To record purchase of inventory on credit

Sheet Part 4
A1: FIFO
A2: Part 4
A4: Purchases: | B4: Beginning | C4: 600 | D4: 105 | E4: =+C4*D4 -> 63000
B5: 42048 | C5: 200 | D5: 109 | E5: =+C5*D5 -> 21800
B6: 42221 | C6: 345 | D6: 112 | E6: =+C6*D6 -> 38640
C7: =SUM(C4:C6) -> 1145 | E7: =SUM(E4:E6) -> 123440
A9: Sales: | B9: 42050 | C9: 300 | D9: 105 | E9: =+C9*D9 -> 31500
B11: 42226 | C11: 300 | D11: 105 | E11: =+C11*D11 -> 31500
C12: 35 | D12: 109 | E12: =+C12*D12 -> 3815
E13: =SUM(E9:E12) -> 66815 | F13: Cost of Goods Sold
A18: Remaining | B18: Beginning | C18: 0 | D18: 105 | E18: =+C18*D18 -> 0
B19: 42048 | C19: =+C5-C12 -> 165 | D19: 109 | E19: =+C19*D19 -> 17985
B20: 42221 | C20: =+C6 -> 345 | D20: =D6 -> 112 | E20: =+C20*D20 -> 38640
C21: =SUM(C18:C20) -> 510 | E21: =SUM(E18:E20) -> 56625 | F21: Ending Inventory
A30: WEIGHTED AVERAGE
A31: =+A2 -> Part 4
A33: Average cost per unit:
A34: = | B34: GAFS $ | F34: Ending inventory in units:
B35: GAFS # | F35: Opening inventory | H35: 600
F36: Purchased 200+345= | H36: 545
A37: = | B37: Opening + purchases in $ | F37: Goods avail for sale | H37: =SUM(H35:H36) -> 1145
B38: Opening + purchases in # | F38: Sold 300 + 335 = | H38: =-1*635 -> -635
F39: Ending Inventory | H39: =SUM(H37:H38) -> 510
A40: = | B40: (600x105$) + (200x$109 + 345x112$)
B41: 600 + 200 + 345 | F41: Merchandise Inventory at year end:
H42: =+D43 -> 107.80786
A43: = | B43: =+'Part 1a-FIFO'!D24 -> 123440 | C43: = | D43: =+B43/B44 -> 107.80786 | G43: x | H43: =+H39 -> 510
B44: =+'Part 1a-FIFO'!B24 -> 1145 | H44: =+H43*H42 -> 54982.009
F46: Cost of Goods Sold:
H47: =+D43 -> 107.80786
G48: x | H48: =-1*H38 -> 635
H49: =+H47*H48 -> 68457.991
